{
  "$schema": "../gen/schemas/desktop-schema.json",
  "identifier": "default",
  "description": "Core capabilities for the Spine-IQ main window and tray.",
  "windows": ["main"],
  "permissions": [
    "core:default",
    "core:window:allow-show",
    "core:window:allow-hide",
    "core:window:allow-set-focus",
    "core:window:allow-close",
    "core:app:allow-version",
    "core:event:default",
    "opener:default",
    "notification:default",
    "autostart:allow-enable",
    "autostart:allow-disable",
    "autostart:allow-is-enabled"
  ]
}
